<annotation>
	<folder>train ch</folder>
	<filename>474.jpg</filename>
	<path>C:\Users\mdemarle\Documents\projet m\train ch\474.jpg</path>
	<source>
		<database>Unknown</database>
	</source>
	<size>
		<width>800</width>
		<height>600</height>
		<depth>3</depth>
	</size>
	<segmented>0</segmented>
	<object>
		<name>champignon</name>
		<pose>Unspecified</pose>
		<truncated>0</truncated>
		<difficult>0</difficult>
		<bndbox>
			<xmin>446</xmin>
			<ymin>141</ymin>
			<xmax>591</xmax>
			<ymax>215</ymax>
		</bndbox>
	</object>
	<object>
		<name>champignon</name>
		<pose>Unspecified</pose>
		<truncated>0</truncated>
		<difficult>0</difficult>
		<bndbox>
			<xmin>466</xmin>
			<ymin>398</ymin>
			<xmax>570</xmax>
			<ymax>466</ymax>
		</bndbox>
	</object>
	<object>
		<name>champignon</name>
		<pose>Unspecified</pose>
		<truncated>0</truncated>
		<difficult>0</difficult>
		<bndbox>
			<xmin>591</xmin>
			<ymin>345</ymin>
			<xmax>748</xmax>
			<ymax>432</ymax>
		</bndbox>
	</object>
</annotation>
