<annotation>
	<folder>champignon</folder>
	<filename>103.jpg</filename>
	<path>C:\Users\mdemarle\Documents\projet m\object_detection_demo\data\images\train\champignon\103.jpg</path>
	<source>
		<database>Unknown</database>
	</source>
	<size>
		<width>800</width>
		<height>600</height>
		<depth>3</depth>
	</size>
	<segmented>0</segmented>
	<object>
		<name>champignon</name>
		<pose>Unspecified</pose>
		<truncated>0</truncated>
		<difficult>0</difficult>
		<bndbox>
			<xmin>466</xmin>
			<ymin>120</ymin>
			<xmax>578</xmax>
			<ymax>290</ymax>
		</bndbox>
	</object>
	<object>
		<name>champignon</name>
		<pose>Unspecified</pose>
		<truncated>0</truncated>
		<difficult>0</difficult>
		<bndbox>
			<xmin>217</xmin>
			<ymin>368</ymin>
			<xmax>353</xmax>
			<ymax>566</ymax>
		</bndbox>
	</object>
	<object>
		<name>champignon</name>
		<pose>Unspecified</pose>
		<truncated>0</truncated>
		<difficult>0</difficult>
		<bndbox>
			<xmin>33</xmin>
			<ymin>115</ymin>
			<xmax>159</xmax>
			<ymax>291</ymax>
		</bndbox>
	</object>
</annotation>
