<annotation>
	<folder>test</folder>
	<filename>image (153).jpg</filename>
	<path>C:\Users\mdemarle\Documents\projet m\object_detection_demo\data\images\train\image (153).jpg</path>
	<source>
		<database>Unknown</database>
	</source>
	<size>
		<width>800</width>
		<height>600</height>
		<depth>3</depth>
	</size>
	<segmented>0</segmented>
	<object>
		<name>oeuf</name>
		<pose>Unspecified</pose>
		<truncated>0</truncated>
		<difficult>0</difficult>
		<bndbox>
			<xmin>297</xmin>
			<ymin>204</ymin>
			<xmax>575</xmax>
			<ymax>348</ymax>
		</bndbox>
	</object>
</annotation>